mono_pay/__init__.py
mono_pay/client.py
mono_pay/payment.py
mono_pay/webhook.py
tests/__init__.py
tests/test_mono_pay.py
py_mono_bank_pay-0.1.1.dist-info/LICENSE
py_mono_bank_pay-0.1.1.dist-info/METADATA
py_mono_bank_pay-0.1.1.dist-info/WHEEL
py_mono_bank_pay-0.1.1.dist-info/top_level.txt
py_mono_bank_pay-0.1.1.dist-info/RECORD
