Metadata-Version: 2.1
Name: py_mono_bank_pay
Version: 0.1.1
Summary: A client library for Monobank merchant API
Home-page: https://github.com/ithekozub/py_mono_bank_pay
Author: Grechka Konstantin
Author-email: ytextsocks@gmail.com
Classifier: Programming Language :: Python :: 3
Classifier: License :: OSI Approved :: MIT License
Classifier: Operating System :: OS Independent
Requires-Python: >=3.6
License-File: LICENSE
Requires-Dist: requests
Requires-Dist: ecdsa
